plazma_chess/__init__.py
plazma_chess/engine.py
plazma_chess-1.2.2.dist-info/licenses/LICENCE
plazma_chess-1.2.2.dist-info/METADATA
plazma_chess-1.2.2.dist-info/WHEEL
plazma_chess-1.2.2.dist-info/entry_points.txt
plazma_chess-1.2.2.dist-info/top_level.txt
plazma_chess-1.2.2.dist-info/RECORD
