Metadata-Version: 2.4
Name: plazma-chess
Version: 1.2.2
Summary: A fully function chess engine written in python
Author-email: CaptainDeathead <unstableplazma@gmail.com>
Project-URL: Homepage, https://github.com/CaptainDeathead/plazma-chess-engine
Keywords: chess,engine,game
Classifier: License :: OSI Approved :: MIT License
Classifier: Programming Language :: Python
Classifier: Programming Language :: Python :: 3
Requires-Python: >3
License-File: LICENCE
Provides-Extra: dev
Dynamic: license-file
